{
  "project_info": {
    "project_number": "569875391301",
    "firebase_url": "https://kiviremote2.firebaseio.com",
    "project_id": "kiviremote2",
    "storage_bucket": "kiviremote2.appspot.com"
  },
  "client": [
    {
      "client_info": {
        "mobilesdk_app_id": "1:569875391301:android:fab3ff95f8b8256d23d42c",
        "android_client_info": {
          "package_name": "com.kivi.remote"
        }
      },
      "oauth_client": [
        {
          "client_id": "569875391301-jepifoai1jb29spgbcnp0vln1jcv899s.apps.googleusercontent.com",
          "client_type": 1,
          "android_info": {
            "package_name": "com.kivi.remote",
            "certificate_hash": "d513caba4ed29b67024a35fe9349a73cd7270c3e"
          }
        },
        {
          "client_id": "569875391301-o7ncklufr57q4p9fg2mkn34g4uje42fl.apps.googleusercontent.com",
          "client_type": 3
        }
      ],
      "api_key": [
        {
          "current_key": "AIzaSyDtS3DazG2t81aihEsftCrsy9859kTPFTk"
        }
      ],
      "services": {
        "appinvite_service": {
          "other_platform_oauth_client": [
            {
              "client_id": "569875391301-o7ncklufr57q4p9fg2mkn34g4uje42fl.apps.googleusercontent.com",
              "client_type": 3
            }
          ]
        }
      }
    },
    {
      "client_info": {
        "mobilesdk_app_id": "1:569875391301:android:c32d76adedd01fb423d42c",
        "android_client_info": {
          "package_name": "com.kivi.remote.debug"
        }
      },
      "oauth_client": [
        {
          "client_id": "569875391301-dqd8m38vh86hof8c91dmknd4f5h4c0f1.apps.googleusercontent.com",
          "client_type": 1,
          "android_info": {
            "package_name": "com.kivi.remote.debug",
            "certificate_hash": "d513caba4ed29b67024a35fe9349a73cd7270c3e"
          }
        },
        {
          "client_id": "569875391301-o7ncklufr57q4p9fg2mkn34g4uje42fl.apps.googleusercontent.com",
          "client_type": 3
        }
      ],
      "api_key": [
        {
          "current_key": "AIzaSyDtS3DazG2t81aihEsftCrsy9859kTPFTk"
        }
      ],
      "services": {
        "appinvite_service": {
          "other_platform_oauth_client": [
            {
              "client_id": "569875391301-o7ncklufr57q4p9fg2mkn34g4uje42fl.apps.googleusercontent.com",
              "client_type": 3
            }
          ]
        }
      }
    }
  ],
  "configuration_version": "1"
}